KUtils/KView.py
KUtils/Typing.py
KUtils/__init__.py
KUtils/Helpers/__init__.py
KUtils/Helpers/Argpack/Argpack.py
KUtils/Helpers/Argpack/__init__.py
KUtils/Helpers/Beans/BeanMeta.py
KUtils/Helpers/Beans/__init__.py
KUtils/Helpers/CacheMan/Cache.py
KUtils/Helpers/CacheMan/CacheMan.py
KUtils/Helpers/CacheMan/VersionedCacheMixin.py
KUtils/Helpers/CacheMan/__init__.py
KUtils/Helpers/CodeGen/BoilerplateWriter.py
KUtils/Helpers/CodeGen/Common.py
KUtils/Helpers/CodeGen/Playground.generated.py
KUtils/Helpers/CodeGen/Playground.py
KUtils/Helpers/CodeGen/Writer.py
KUtils/Helpers/CodeGen/__init__.py
KUtils/Helpers/CodeGen/runner.py
KUtils/Helpers/CodeGen/Boilerplates/AttrMixin.py
KUtils/Helpers/CodeGen/Boilerplates/__init__.py
KUtils/Helpers/ComFunc/ComFunc.py
KUtils/Helpers/ComFunc/__init__.py
KUtils/Helpers/DataClass/DataClass.py
KUtils/Helpers/DataClass/__init__.py
KUtils/Helpers/KBuf/KBuf.py
KUtils/Helpers/KBuf/KDim.py
KUtils/Helpers/KBuf/__init__.py
KUtils/Helpers/KGenric/KGeneric.py
KUtils/Helpers/KGenric/__init__.py
KUtils/Helpers/KProp/Property.py
KUtils/Helpers/KProp/__init__.py
KUtils/Helpers/KView/Object3D.py
KUtils/Helpers/KView/Plane.py
KUtils/Helpers/KView/Shapes.py
KUtils/Helpers/KView/Transform3D.py
KUtils/Helpers/KView/VisualizeMixin.py
KUtils/Helpers/KView/__init__.py
KUtils/Helpers/KView/fns.py
KUtils/Helpers/KView/helpers.py
KUtils/Helpers/LayerMask/LayerMask.py
KUtils/Helpers/LayerMask/__init__.py
KUtils/Helpers/Mixins/BaseMixin.py
KUtils/Helpers/Mixins/__init__.py
KUtils/Helpers/MonkeyPatch/MonkeyPatch.py
KUtils/Helpers/MonkeyPatch/__init__.py
KUtils/Helpers/Namespace/Namespace.py
KUtils/Helpers/Namespace/__init__.py
KUtils/Helpers/ProxyHelper/__init__.py
KUtils/Helpers/RouterBuilder/RouterBuilder.py
KUtils/Helpers/RouterBuilder/__init__.py
KUtils/Helpers/SafeContainer/SafeContainer.py
KUtils/Helpers/SafeContainer/__init__.py
KUtils/Helpers/Strenum/AutoEnum.py
KUtils/Helpers/Strenum/Strenum.py
KUtils/Helpers/Strenum/__init__.py
kutilz-0.1.104.dist-info/METADATA
kutilz-0.1.104.dist-info/WHEEL
kutilz-0.1.104.dist-info/RECORD
