Metadata-Version: 2.4
Name: KUtilz
Version: 0.1.104
Summary: Quality of life utils that apply to vanilla python
Author-email: Xukai Liu <liu.xukai.34@gmail.com>
License: MIT
Classifier: License :: OSI Approved :: MIT License
Classifier: Operating System :: OS Independent
Classifier: Programming Language :: Python :: 3
Requires-Python: >=3.8
Requires-Dist: anytree
Requires-Dist: bidict==0.23.1
Requires-Dist: cycler==0.12.1
Requires-Dist: diskcache==5.6.3
Requires-Dist: fonttools==4.54.1
Requires-Dist: imageio==2.35.1
Requires-Dist: kiwisolver==1.4.7
Requires-Dist: lazy-loader==0.4
Requires-Dist: matplotlib==3.7.5
Requires-Dist: mpmath==1.3.0
Requires-Dist: networkx==3.1
Requires-Dist: numpy==1.24.4
Requires-Dist: packaging==24.1
Requires-Dist: param==2.1.1
Requires-Dist: pillow==10.4.0
Requires-Dist: pydantic-core==2.23.4
Requires-Dist: pydantic==2.9.2
Requires-Dist: pyparsing==3.1.4
Requires-Dist: python-dateutil==2.9.0.post0
Requires-Dist: pytz==2024.2
Requires-Dist: pywavelets==1.4.1
Requires-Dist: pyyaml==6.0.2
Requires-Dist: seaborn==0.13.2
Requires-Dist: tifffile==2023.7.10
Requires-Dist: tqdm
Requires-Dist: typing-extensions==4.12.2
Requires-Dist: tzdata==2024.2
Requires-Dist: zipp==3.20.2
